README.rst
pydotenv.py
setup.py
pydotenv.egg-info/PKG-INFO
pydotenv.egg-info/SOURCES.txt
pydotenv.egg-info/dependency_links.txt
pydotenv.egg-info/top_level.txt