Metadata-Version: 1.1
Name: pydotenv
Version: 0.0.3
Summary: A libray to write .env files
Home-page: https://github.com/alej0varas/pydotenv
Author: Alexandre Varas
Author-email: alej0varas@gmail.com
License: GNU Library or Lesser General Public License (LGPL)
Platform: UNKNOWN
Classifier: Development Status :: 3 - Alpha
Classifier: Intended Audience :: Developers
Classifier: License :: OSI Approved :: GNU Library or Lesser General Public License (LGPL)
Classifier: Operating System :: OS Independent
Classifier: Topic :: Software Development :: Libraries
Classifier: Programming Language :: Python
Classifier: Programming Language :: Python :: 3
